{
  "Object":{"toString()":"String"},
  "Integer":{"parseInt(String)":"int"},
  "Firestore": {"Collection(String)":  "CollectionReference"},
  "CollectionReference": {"add(Map<String,Object>)": "DocumentReference","Document()": "DocumentReference","Document(String)": "DocumentReference",
    "GetSnapshotAsync()": "QuerySnapshot","WhereEqualTo(String,String)": "Query","WhereGreaterThan(String,int)": "Query","WhereGreaterThan(String,String)": "Query",
    "WhereGreaterThanOrEqualTo(String,String)": "Query","WhereGreaterThanOrEqualTo(String,int)": "Query",
    "WhereArrayContains(String,String)": "Query","WhereLessThanOrEqualTo(String,String)": "Query",
    "WhereLessThanOrEqualTo(String,int)": "Query","WhereLessThanOrEqualTo(String,String)": "whereField(/0, isLessThanOrEqualTo: /1)",
    "WhereLessThanOrEqualTo(String,int)": "whereField(0, isLessThanOrEqualTo: /1)"
  },
  "QuerySnapshot":{
    "Documents()": "QuerySnapshot"
  }


}